{
    "last_announcement_id": 0,
    "show_announcements": true,
    "current_theme": "Custom",
    "enable_analytics": true,
    "user_name": "User",
    "pid_bot_modes": {},
    "pid_kickoff_enabled": {
        "2560": false
    },
    "pid_ballcam_enabled": {
        "9340": true,
        "2560": true,
        "7284": true,
        "13768": true
    },
    "pid_demo_enabled": {},
    "admin_warning_shown": true,
    "bot_builder": {
        "active_profile": "kingvon.pub  config",
        "profiles": {
            "None": {
                "description": "Default profile: Nexto for kickoff, Vortex for gameplay.",
                "rules": [
                    {
                        "id": "default",
                        "enabled": true,
                        "condition": {
                            "type": "default"
                        },
                        "bot": "vortex",
                        "priority": 1
                    }
                ]
            },
            "kingvon.pub  config": {
                "description": "Custom profile: kingvon.pub  config",
                "rules": [
                    {
                        "id": "rule_1773425461",
                        "enabled": true,
                        "condition": {
                            "type": "kickoff"
                        },
                        "guards": [],
                        "bot": "nexto",
                        "cooldown": 0.0,
                        "priority": 1
                    },
                    {
                        "id": "rule_1773425417",
                        "enabled": true,
                        "condition": {
                            "type": "is_third_man"
                        },
                        "guards": [],
                        "bot": "nexto",
                        "cooldown": 0.0,
                        "priority": 2
                    },
                    {
                        "id": "rule_1773425426",
                        "enabled": true,
                        "condition": {
                            "type": "is_second_man"
                        },
                        "guards": [],
                        "bot": "nexto",
                        "cooldown": 0.0,
                        "priority": 3
                    },
                    {
                        "id": "rule_1773425447",
                        "enabled": true,
                        "condition": {
                            "type": "ball_height",
                            "operator": ">",
                            "value": 300.0
                        },
                        "guards": [],
                        "bot": "vortex",
                        "cooldown": 0.0,
                        "priority": 4
                    },
                    {
                        "id": "rule_1773522697",
                        "enabled": true,
                        "condition": {
                            "type": "airborne"
                        },
                        "guards": [],
                        "bot": "vortex",
                        "cooldown": 0.0,
                        "priority": 5
                    },
                    {
                        "id": "rule_1773425481",
                        "enabled": true,
                        "condition": {
                            "type": "default"
                        },
                        "guards": [],
                        "bot": "nexto",
                        "cooldown": 0.0,
                        "priority": 6
                    }
                ]
            }
        },
        "enabled": true,
        "demo_override": true
    },
    "humanizer_settings": {
        "nexto": {
            "enabled": true,
            "noise_amount": 2.0,
            "smoothing": 3.0,
            "varied_hold_times": false,
            "hold_time_delay": 0.0,
            "variable_tick_rate": false,
            "tick_rate_value": 0.0
        },
        "vortex": {
            "enabled": true,
            "noise_amount": 1.0,
            "smoothing": 4.0,
            "varied_hold_times": false,
            "hold_time_delay": 0.0,
            "variable_tick_rate": true,
            "tick_rate_value": 0
        },
        "ice_poseidon": {
            "enabled": false,
            "noise_amount": 2.0,
            "smoothing": 3.0,
            "varied_hold_times": false,
            "hold_time_delay": 0.0,
            "variable_tick_rate": true,
            "tick_rate_value": 0
        },
        "demo": {
            "enabled": false,
            "noise_amount": 3.0,
            "smoothing": 2.0,
            "varied_hold_times": false,
            "hold_time_delay": 0.0,
            "variable_tick_rate": false,
            "tick_rate_value": 0
        }
    },
    "custom_theme_colors": {
        "BG": "#050505",
        "SIDEBAR": "#0A0A0A",
        "MAIN_CONTENT": "#050505",
        "CARD": "#111111",
        "CARD_HOVER": "#1A1A1A",
        "CARD_BORDER": "#e83554",
        "CARD_BORDER_HOVER": "#ff3f64",
        "ACCENT": "#e83554",
        "ACCENT_HOVER": "#b92a43",
        "TEXT": "#FFFFFF",
        "TEXT_SECONDARY": "#B0B0B0",
        "LINK": "#ff446d",
        "GREEN": "#27AE60",
        "DARK_GREEN": "#1B8246",
        "YELLOW": "#F1C40F",
        "IDLE": "#00BFFF",
        "STOP": "#C0392B",
        "STOP_HOVER": "#A93226",
        "TEXT_ON_ACCENT": "#FFFFFF"
    },
    "pid_bot_versions": {
        "2596": "legacy_62",
        "13548": "legacy_62"
    }
}